yesglot/__init__.py
yesglot/apps.py
yesglot/llm.py
yesglot/settings.py
yesglot/translation_files.py
yesglot/utils.py
yesglot/management/__init__.py
yesglot/management/commands/__init__.py
yesglot/management/commands/translatemessages.py
yesglot-0.1.0a4.dist-info/METADATA
yesglot-0.1.0a4.dist-info/WHEEL
yesglot-0.1.0a4.dist-info/licenses/LICENSE
yesglot-0.1.0a4.dist-info/RECORD
