Metadata-Version: 2.4
Name: yesglot
Version: 0.1.0a4
Summary: Django app for seamless AI-assisted translation of .po files.
Project-URL: Homepage, https://github.com/efe/yesglot
Project-URL: Issues, https://github.com/efe/yesglot/issues
Author-email: Efe Öge <efeoge@gmail.com>
License: Mozilla Public License Version 2.0
License-File: LICENSE
Keywords: app,django,llm,translation
Classifier: Framework :: Django
Classifier: Framework :: Django :: 4
Classifier: Framework :: Django :: 5
Classifier: License :: OSI Approved :: MIT License
Classifier: Operating System :: OS Independent
Classifier: Programming Language :: Python :: 3
Requires-Python: >=3.9
Requires-Dist: babel>=2.17
Requires-Dist: django>=4.2
Requires-Dist: litellm>=1.75.8
Requires-Dist: polib>=1.2
Requires-Dist: tiktoken>=0.11
